{"is_source_file": false, "format": "", "description": "", "external_files": [], "external_methods": [], "published": [], "classes": [], "methods": [], "calls": [], "search-terms": [], "state": 2, "file_id": 5, "knowledge_revision": 12, "git_revision": "5098c55ec72733f35e50a536b01660725d21089d", "hash": "0c9f36dfd1a6dee9fa952c06ab7d9563", "format-version": 4, "code-base-name": "todo_database", "filename": "todo_database/db_visualizer/package.json", "revision_history": [{"12": "5098c55ec72733f35e50a536b01660725d21089d"}]}